setup.py
chainedci/__init__.py
chainedci/artifact.py
chainedci/artifact_src.py
chainedci/chainedci
chainedci/cli.py
chainedci/config.py
chainedci/default_chainedci.yml
chainedci/env_vars.py
chainedci/http_adapter.py
chainedci/init_project.py
chainedci/inventory.py
chainedci/log.py
chainedci/options.py
chainedci/parser.py
chainedci/pipeline.py
chainedci/scenario.py
chainedci/step.py
chainedci/tools.py
chainedci/version.py
chainedci/static/inventory
chainedci/static/projectA.yml
chainedci/static/projectA_config1.yml
chainedci/static/projectA_config2.yml
chainedci/templates/all.yml.tpl
chainedci/templates/main.yml.tpl
chainedci/templates/scenario.yml.tpl
chainedci-1.6.4.data/scripts/chainedci
tests/__init__.py
tests/tests_lib.py
chainedci-1.6.4.dist-info/METADATA
chainedci-1.6.4.dist-info/WHEEL
chainedci-1.6.4.dist-info/top_level.txt
chainedci-1.6.4.dist-info/RECORD
