Metadata-Version: 2.1
Name: chainedci
Version: 1.6.4
Summary: Chaine Gitlab CI pipelines
Home-page: https://gitlab.com/Orange-OpenSource/lfn/ci_cd/chained-ci
Author: Orange OpenSource
License: Apache 2.0
Requires-Dist: ansible-core ==2.16.3
Requires-Dist: GitPython ==3.1.41
Requires-Dist: Jinja2 ==3.1.3
Requires-Dist: requests ==2.31.0
Requires-Dist: schema ==0.7.5
Requires-Dist: urllib3 ==2.1.0
